<mvc:View controllerName="sap.hanacli.tables.controller.containers-ui" height="100%" width="100%"
	xmlns:l="sap.ui.layout"
	xmlns:f="sap.ui.layout.form"
	xmlns:mvc="sap.ui.core.mvc"
	xmlns:core="sap.ui.core"
	xmlns="sap.m">
	<ScrollContainer id="scrollContainer" height="100%" width="100%" vertical="true" focusable="true">
		<f:SimpleForm id="SimpleFormToolbarContainers" editable="true" layout="ResponsiveGridLayout" adjustLabelSpan="true" singleContainerFullSize="false" ariaLabelledBy="Title1">
			<f:toolbar>
				<core:Fragment fragmentName="sap.hanacli.tables.view.reuse.toolbar" type="XML"/>
			</f:toolbar>
			 	<f:content>

				<Toolbar id="targetToolbar" ariaLabelledBy="TitleContainers">
					<Title id="TitleContainers" text="{i18nReuse>gui.target}"/>
					<ToolbarSpacer id="spacerContainers"/>
					<Button id="settingsButton" icon="sap-icon://settings" tooltip="{i18nReuse>gui.targetDetails}" press=".openUrl('/ui/#systeminfo-ui', true)" />
				</Toolbar>

				<Label id="labelContainerGroup" text="{i18nReuse>containerGroup}" required="true"/>
				<Input id="containerGroup" value="{/containerGroup}" >
				</Input>
				<Label id="labelContainer" text="{i18nReuse>container}" required="true"/>
				<Input id="container" value="{/container}">
				</Input>
				<Label id="labelLimit" text="{i18nReuse>limit}" required="true"/>
				<Input id="limit" value="{/limit}" />

				<core:Fragment fragmentName="sap.hanacli.common.view.Connection" type="XML"/>
				<core:Fragment fragmentName="sap.hanacli.common.view.Debug" type="XML"/>

			</f:content>
		</f:SimpleForm>

	
	<core:Fragment fragmentName="sap.hanacli.tables.view.reuse.table" type="XML"/>
	</ScrollContainer>
</mvc:View>